MANIFEST.in
README.md
requirements.txt
setup.cfg
setup.py
dapipe.egg-info/PKG-INFO
dapipe.egg-info/SOURCES.txt
dapipe.egg-info/dependency_links.txt
dapipe.egg-info/not-zip-safe
dapipe.egg-info/requires.txt
dapipe.egg-info/top_level.txt
dpipe/__init__.py
dpipe/datasets.py
dpipe/datasets_test.py
dpipe/factories.py
dpipe/factories_test.py
dpipe/utils.py