Metadata-Version: 2.1
Name: dapipe
Version: 0.2.1
Summary: Creates dataset builder objects
Home-page: https://github.com/aiporre/multidataloader.git
Author: Ariel Iporre
Author-email: ariel.iporre.rivas@gmail.com
License: Apache License Version 2.0 
Download-URL: https://github.com/aiporre/multidataloader/archive/v0.2.1.tar.gz
Platform: UNKNOWN
Classifier: Development Status :: 3 - Alpha
Classifier: Intended Audience :: Developers
Classifier: Topic :: Software Development :: Build Tools
Classifier: License :: OSI Approved :: Apache Software License
Classifier: Programming Language :: Python :: 3.7
